setup.py
somecode/__init__.py
somecode/age_plot.py
somecode/bars.py
somecode/cooc_plot.py
somecode/data_frame.py
somecode/data_prep.py
somecode/flatfile.py
somecode/freq_plot.py
somecode/header.py
somecode/hist_plot.py
somecode/keys.py
somecode/neg2_plot.py
somecode/neg_plot.py
somecode/pretty.py
somecode/retweet_plot.py
somecode/search.py
somecode/semantics.py
somecode/stopword.py
somecode/stream.py
somecode/timeline.py
somecode.egg-info/PKG-INFO
somecode.egg-info/SOURCES.txt
somecode.egg-info/dependency_links.txt
somecode.egg-info/requires.txt
somecode.egg-info/top_level.txt