Metadata-Version: 1.1
Name: somecode
Version: 0.9.9
Summary: Somecode Twitter Science and Research Platform
Home-page: http://botlab.io
Author: Mikko Kotila
Author-email: mailme@mikkokotila.com
License: MIT
Download-URL: https://github.com/S0MEC0DE/
Platform: UNKNOWN
Classifier: Intended Audience :: Science/Research
Classifier: Programming Language :: Python :: 2.7
Classifier: Operating System :: POSIX
Classifier: Operating System :: Unix
Classifier: Operating System :: MacOS
